tests/__init__.py
tests/conftest.py
tests/test_advanced_config.py
tests/test_basic_config.py
tests/test_doctype_checking.py
tests/test_sqlite_output.py
tests/test_xmlcollectiontotabular.py
tests/test_xmldoctotabular.py
xmltotabular/__init__.py
xmltotabular/_version.py
xmltotabular/sqlite_db.py
xmltotabular/utils.py
xmltotabular/xmlcollectiontotabular.py
xmltotabular/xmldoctotabular.py
xmltotabular-0.9.1.dist-info/LICENSE
xmltotabular-0.9.1.dist-info/METADATA
xmltotabular-0.9.1.dist-info/WHEEL
xmltotabular-0.9.1.dist-info/top_level.txt
xmltotabular-0.9.1.dist-info/RECORD
