Metadata-Version: 2.1
Name: xmltotabular
Version: 0.9.1
Summary: Covert XML to tabular data according to YAML configuration
Home-page: https://github.com/simonwiles/xmltotabular
Author: Simon Wiles
Author-email: simonjwiles@gmail.com
License: UNKNOWN
Platform: UNKNOWN
Classifier: Programming Language :: Python :: 3.6
Classifier: Programming Language :: Python :: 3.7
Classifier: Programming Language :: Python :: 3.8
Classifier: Programming Language :: Python :: 3.9
Classifier: Programming Language :: Python :: 3.10
Classifier: License :: OSI Approved :: MIT License
Classifier: Operating System :: OS Independent
Classifier: Development Status :: 3 - Alpha
Requires-Python: >=3.6
License-File: LICENSE
Requires-Dist: lxml
Requires-Dist: pyyaml
Requires-Dist: termcolor
Requires-Dist: multiprocess ; python_version < "3.7"
